rl_framework/__init__.py
rl_framework/agent/__init__.py
rl_framework/agent/base_agent.py
rl_framework/agent/imitation/__init__.py
rl_framework/agent/imitation/d3rlpy/__init__.py
rl_framework/agent/imitation/d3rlpy/d3rlpy.py
rl_framework/agent/imitation/episode_sequence.py
rl_framework/agent/imitation/imitation/__init__.py
rl_framework/agent/imitation/imitation/algorithms/__init__.py
rl_framework/agent/imitation/imitation/algorithms/airl.py
rl_framework/agent/imitation/imitation/algorithms/algorithm_wrapper.py
rl_framework/agent/imitation/imitation/algorithms/bc.py
rl_framework/agent/imitation/imitation/algorithms/density.py
rl_framework/agent/imitation/imitation/algorithms/gail.py
rl_framework/agent/imitation/imitation/algorithms/sqil.py
rl_framework/agent/imitation/imitation/imitation.py
rl_framework/agent/imitation_learning_agent.py
rl_framework/agent/reinforcement/__init__.py
rl_framework/agent/reinforcement/async_stable_baselines.py
rl_framework/agent/reinforcement/custom_agent.py
rl_framework/agent/reinforcement/custom_algorithms/__init__.py
rl_framework/agent/reinforcement/custom_algorithms/base_custom_algorithm.py
rl_framework/agent/reinforcement/custom_algorithms/q_learning.py
rl_framework/agent/reinforcement/stable_baselines.py
rl_framework/agent/reinforcement_learning_agent.py
rl_framework/util/__init__.py
rl_framework/util/connector/__init__.py
rl_framework/util/connector/base_connector.py
rl_framework/util/connector/clearml_connector.py
rl_framework/util/connector/dummy_connector.py
rl_framework/util/connector/hugging_face_connector.py
rl_framework/util/features_extractor_utils.py
rl_framework/util/sb3_training_callbacks.py
rl_framework/util/types.py
rl_framework/util/util.py
rl_framework/util/video_recording.py
reinforcement_learning_framework-0.9.6.dist-info/LICENSE
reinforcement_learning_framework-0.9.6.dist-info/METADATA
reinforcement_learning_framework-0.9.6.dist-info/WHEEL
reinforcement_learning_framework-0.9.6.dist-info/RECORD
