Metadata-Version: 2.1
Name: reinforcement-learning-framework
Version: 0.9.6
Summary: An easy-to-read Reinforcement Learning (RL) framework. Provides standardized interfaces and implementations to various Reinforcement Learning methods and utilities.
Home-page: https://github.com/alexander-zap/reinforcement-learning-framework
License: MIT
Keywords: reinforcement learning,rl,imitation learning
Author: Alexander Zap
Requires-Python: >=3.9,<4.0
Classifier: Development Status :: 5 - Production/Stable
Classifier: Intended Audience :: Developers
Classifier: License :: OSI Approved :: MIT License
Classifier: Operating System :: OS Independent
Classifier: Programming Language :: Python
Classifier: Programming Language :: Python :: 3
Classifier: Programming Language :: Python :: 3.9
Classifier: Programming Language :: Python :: 3.10
Classifier: Programming Language :: Python :: 3.11
Classifier: Programming Language :: Python :: 3.12
Classifier: Topic :: Software Development :: Libraries :: Python Modules
Requires-Dist: async-gym-agents (>=0.1.6,<0.2.0)
Requires-Dist: clearml (>=1.14.1,<2.0.0)
Requires-Dist: d3rlpy (>=2.6,<3.0)
Requires-Dist: dm-env-rpc (>=1.1.6,<2.0.0)
Requires-Dist: gymnasium (>=0.29,<0.30)
Requires-Dist: huggingface_hub (>=0.19,<0.20)
Requires-Dist: imageio (>=2.33.0,<3.0.0)
Requires-Dist: imitation (>=1.0.0,<2.0.0)
Requires-Dist: moviepy (>=1.0.3,<2.0.0)
Requires-Dist: numpy (>=1.26.3,<2.0.0)
Requires-Dist: onnx (>=1.15.0,<2.0.0)
Requires-Dist: pettingzoo (>=1.24.3,<2.0.0)
Requires-Dist: protobuf (>=3.20,<3.21)
Requires-Dist: pyarrow (<=20.0.0)
Requires-Dist: pyarrow-hotfix (>=0.6,<0.7)
Requires-Dist: stable-baselines3[extra] (>=2.2,<3.0)
Requires-Dist: supersuit (>=3.9.3,<4.0.0)
Requires-Dist: tqdm (>=4.66,<5.0)
